doepy/__init__.py
doepy/build.py
doepy/doe_functions.py
doepy/pydoe_corrected.py
doepy/read_write.py
doepy-0.0.1.dist-info/LICENSE
doepy-0.0.1.dist-info/METADATA
doepy-0.0.1.dist-info/WHEEL
doepy-0.0.1.dist-info/top_level.txt
doepy-0.0.1.dist-info/RECORD
