Metadata-Version: 2.1
Name: doepy
Version: 0.0.1
Summary: Design of experiments generator with simple CSV input/output options
Home-page: https://github.com/tirthajyoti/doepy
Author: Tirthajyoti Sarkar
Author-email: tirthajyoti@gmail.com
License: MIT License
Download-URL: https://github.com/tirthajyoti/doepy/archive/0.0.1.tar.gz
Keywords: DOE,science,physics,engineering,design of experiments,experimental design,optimization,statistics,python
Platform: UNKNOWN
Classifier: Development Status :: 3 - Alpha
Classifier: Intended Audience :: Education
Classifier: Intended Audience :: Science/Research
Classifier: License :: OSI Approved :: MIT License
Classifier: Operating System :: OS Independent
Classifier: Programming Language :: Python
Classifier: Programming Language :: Python :: 3.4
Classifier: Programming Language :: Python :: 3.5
Classifier: Programming Language :: Python :: 3.6
Classifier: Topic :: Education
Classifier: Topic :: Scientific/Engineering
Classifier: Topic :: Scientific/Engineering :: Mathematics
Classifier: Topic :: Scientific/Engineering :: Physics
Classifier: Topic :: Software Development
Classifier: Topic :: Software Development :: Libraries
Classifier: Topic :: Software Development :: Libraries :: Python Modules
Classifier: Topic :: Utilities
Requires-Dist: pyDOE
Requires-Dist: numpy
Requires-Dist: pandas
Requires-Dist: diversipy
